gazpar2haws/__init__.py
gazpar2haws/__main__.py
gazpar2haws/bridge.py
gazpar2haws/config_utils.py
gazpar2haws/configuration.py
gazpar2haws/date_array.py
gazpar2haws/gazpar.py
gazpar2haws/haws.py
gazpar2haws/model.py
gazpar2haws/pricer.py
gazpar2haws/version.py
gazpar2haws-0.3.3.dist-info/LICENSE
gazpar2haws-0.3.3.dist-info/METADATA
gazpar2haws-0.3.3.dist-info/WHEEL
gazpar2haws-0.3.3.dist-info/RECORD
