Metadata-Version: 2.3
Name: gazpar2haws
Version: 0.3.3
Summary: Gazpar2HAWS is a gateway that reads data history from the GrDF (French gas provider) meter and send it to Home Assistant using WebSocket interface
License: MIT License
Author: Stéphane Senart
Requires-Python: >=3.10
Classifier: Programming Language :: Python :: 3.10
Classifier: Programming Language :: Python :: 3.11
Classifier: Programming Language :: Python :: 3.12
Classifier: Programming Language :: Python :: 3.13
Requires-Dist: pydantic-extra-types (>=2.10.2,<3.0.0)
Requires-Dist: pydantic[email] (>=2.10.6,<3.0.0)
Requires-Dist: pygazpar (>=1.3.1)
Requires-Dist: pyyaml (>=6.0.2)
Requires-Dist: websockets (>=14.1)
